xc/__init__.py
xc/cmd/__init__.py
xc/cmd/docker/__init__.py
xc/cmd/docker/docker.py
xc/cmd/proxy/__init__.py
xc/cmd/proxy/proxy.py
xc/cmd/tmux/__init__.py
xc/cmd/tmux/tmux.py
xc/utils/__init__.py
xc/utils/util.py
xc/xc.py
xc_cli-0.0.6.dist-info/LICENSE
xc_cli-0.0.6.dist-info/METADATA
xc_cli-0.0.6.dist-info/WHEEL
xc_cli-0.0.6.dist-info/entry_points.txt
xc_cli-0.0.6.dist-info/RECORD
